[
  {
    "subject_id": 1,
    "front_content": "I/O接口的功能是什么？",
    "back_content": "**I/O接口功能：**\n\n1. **地址译码和设备选择**\n   - 识别CPU要访问的设备\n\n2. **数据缓冲**\n   - 解决速度匹配问题\n   - 数据寄存器\n\n3. **数据格式转换**\n   - 串/并行转换\n   - 电平转换\n\n4. **控制逻辑**\n   - 接收CPU命令\n   - 向CPU报告状态\n\n5. **中断请求**\n   - I/O完成后向CPU发中断",
    "difficulty_level": 3
  },
  {
    "subject_id": 1,
    "front_content": "I/O接口的编址方式有哪些？",
    "back_content": "**I/O编址方式：**\n\n**1. 统一编址（存储器映射方式）**\n\n- I/O端口与主存单元统一编址\n- 访问I/O用访存指令\n- 无需专门I/O指令\n\n**优点：**\n- 编程方便\n- I/O端口空间大\n\n**缺点：**\n- 占用主存地址空间\n\n**2. 独立编址（I/O映射方式）**\n\n- I/O端口单独编址\n- 使用专门的I/O指令\n\n**优点：**\n- 不占用主存空间\n\n**缺点：**\n- 需专门I/O指令\n\n**x86采用独立编址，ARM采用统一编址**",
    "difficulty_level": 4
  },
  {
    "subject_id": 1,
    "front_content": "程序查询方式的I/O工作原理是什么？",
    "back_content": "**程序查询方式：**\n\nCPU不断查询I/O设备状态，直到设备准备好。\n\n**工作流程：**\n\n```\n1. CPU启动I/O设备\n2. 循环检查设备状态\n   while (状态 != 就绪) {\n       检查状态;\n   }\n3. 执行数据传输\n4. 继续其他操作\n```\n\n**特点：**\n- 简单，硬件成本低\n- CPU效率低（大部分时间在等待）\n- 适合低速设备或实时性要求不高的情况",
    "difficulty_level": 3
  },
  {
    "subject_id": 1,
    "front_content": "程序中断方式的I/O工作原理是什么？",
    "back_content": "**程序中断方式：**\n\nCPU启动I/O后继续执行其他程序，I/O完成后向CPU发中断。\n\n**工作流程：**\n\n```\n1. CPU启动I/O，继续执行程序\n2. I/O设备准备数据\n3. 数据准备好，向CPU发中断请求\n4. CPU响应中断，执行中断服务程序\n5. 处理数据，返回原程序\n```\n\n**特点：**\n- CPU与I/O并行工作\n- 提高CPU利用率\n- 需要中断机制支持\n\n**适用：** 中低速设备",
    "difficulty_level": 4
  },
  {
    "subject_id": 1,
    "front_content": "DMA方式的I/O工作原理是什么？",
    "back_content": "**DMA（Direct Memory Access）：**\n\n数据直接在主存和I/O设备间传输，无需CPU干预。\n\n**DMA工作过程：**\n\n```\n1. CPU初始化DMA：\n   - 主存地址\n   - 传输字数\n   - 操作类型\n   - 启动DMA\n\n2. DMA接管总线控制权\n3. DMA直接控制数据传输\n4. 传输完成，向CPU发中断\n5. CPU处理DMA完成事件\n```\n\n**特点：**\n- CPU只在初始化和结束时参与\n- 传输期间CPU可执行其他程序\n- 高速数据传输\n\n**适用：** 高速块设备（如磁盘）",
    "difficulty_level": 4
  },
  {
    "subject_id": 1,
    "front_content": "DMA有哪几种传输方式？",
    "back_content": "**DMA传输方式：**\n\n**1. 停止CPU访存**\n\n- DMA传输期间CPU停止\n- 简单，但CPU效率低\n\n**2. 周期挪用**\n\n- DMA在CPU不使用存储周期时窃用\n- CPU可能暂停一个周期\n- 效率较高\n\n**3. 交替访存**\n\n- CPU和DMA交替使用存储周期\n- 无冲突，效率最高\n- 需要特殊存储器设计\n\n**推荐：周期挪用**",
    "difficulty_level": 4
  },
  {
    "subject_id": 1,
    "front_content": "中断向量是什么？中断向量表的作用是什么？",
    "back_content": "**中断向量：**\n\n中断服务程序的入口地址。\n\n**中断向量表：**\n\n存放所有中断向量的表格。\n\n**工作原理：**\n\n```\n中断发生 → 中断类型号 → 查中断向量表 → 得到中断向量 → 转中断服务程序\n```\n\n**中断向量表位置：**\n- x86：内存低地址区（0000H开始）\n- ARM：固定地址或向量基地址寄存器\n\n**中断类型号：**\n- 每个中断源有唯一编号\n- 根据编号查表得到向量",
    "difficulty_level": 4
  },
  {
    "subject_id": 1,
    "front_content": "什么是多重中断？如何实现？",
    "back_content": "**多重中断：**\n\n在处理一个中断时，响应更高优先级的中断。\n\n**实现条件：**\n\n1. **中断优先级机制**\n   - 不同中断源有不同优先级\n\n2. **中断屏蔽**\n   - 高优先级中断可打断低优先级中断处理\n   - 通过中断屏蔽寄存器实现\n\n**工作流程：**\n\n```\nCPU执行程序\n    ↓\n中断A发生 → 处理中断A\n    ↓\n中断B发生（优先级更高） → 处理中断B\n    ↓\n中断B完成 → 继续处理中断A\n    ↓\n中断A完成 → 继续执行程序\n```",
    "difficulty_level": 4
  }
]